multiocr/__init__.py
multiocr/base_class.py
multiocr/main.py
multiocr/pipelines/__init__.py
multiocr/pipelines/aws_textract/__init__.py
multiocr/pipelines/aws_textract/engine.py
multiocr/pipelines/doctr_ocr/__init__.py
multiocr/pipelines/doctr_ocr/doctr/__init__.py
multiocr/pipelines/doctr_ocr/doctr/datasets/__init__.py
multiocr/pipelines/doctr_ocr/doctr/datasets/utils.py
multiocr/pipelines/doctr_ocr/doctr/datasets/vocabs.py
multiocr/pipelines/doctr_ocr/doctr/file_utils.py
multiocr/pipelines/doctr_ocr/doctr/io/__init__.py
multiocr/pipelines/doctr_ocr/doctr/io/elements.py
multiocr/pipelines/doctr_ocr/doctr/io/image/__init__.py
multiocr/pipelines/doctr_ocr/doctr/io/image/base.py
multiocr/pipelines/doctr_ocr/doctr/io/image/pytorch.py
multiocr/pipelines/doctr_ocr/doctr/io/image/tensorflow.py
multiocr/pipelines/doctr_ocr/doctr/models/__init__.py
multiocr/pipelines/doctr_ocr/doctr/models/_utils.py
multiocr/pipelines/doctr_ocr/doctr/models/artefacts/__init__.py
multiocr/pipelines/doctr_ocr/doctr/models/artefacts/barcode.py
multiocr/pipelines/doctr_ocr/doctr/models/artefacts/face.py
multiocr/pipelines/doctr_ocr/doctr/models/builder.py
multiocr/pipelines/doctr_ocr/doctr/models/classification/__init__.py
multiocr/pipelines/doctr_ocr/doctr/models/classification/magc_resnet/__init__.py
multiocr/pipelines/doctr_ocr/doctr/models/classification/magc_resnet/pytorch.py
multiocr/pipelines/doctr_ocr/doctr/models/classification/magc_resnet/tensorflow.py
multiocr/pipelines/doctr_ocr/doctr/models/classification/mobilenet/__init__.py
multiocr/pipelines/doctr_ocr/doctr/models/classification/mobilenet/pytorch.py
multiocr/pipelines/doctr_ocr/doctr/models/classification/mobilenet/tensorflow.py
multiocr/pipelines/doctr_ocr/doctr/models/classification/predictor/__init__.py
multiocr/pipelines/doctr_ocr/doctr/models/classification/predictor/pytorch.py
multiocr/pipelines/doctr_ocr/doctr/models/classification/predictor/tensorflow.py
multiocr-0.1.4.dist-info/LICENSE
multiocr-0.1.4.dist-info/METADATA
multiocr-0.1.4.dist-info/WHEEL
multiocr-0.1.4.dist-info/RECORD
