Metadata-Version: 2.1
Name: multiocr
Version: 0.1.4
Summary: 
Author: Aravindh
Author-email: 32878238+s-aravindh@users.noreply.github.com
Requires-Python: >=3.8,<4.0
Classifier: Programming Language :: Python :: 3
Classifier: Programming Language :: Python :: 3.8
Classifier: Programming Language :: Python :: 3.9
Classifier: Programming Language :: Python :: 3.10
Classifier: Programming Language :: Python :: 3.11
Requires-Dist: easyocr (>=1.7.0,<2.0.0)
Requires-Dist: langdetect (>=1.0.9,<2.0.0)
Requires-Dist: paddleocr (>=2.6.1.3,<3.0.0.0)
Requires-Dist: paddlepaddle (>=2.4.2,<3.0.0)
Requires-Dist: pytesseract (>=0.3.10,<0.4.0)
Requires-Dist: unidecode (>=1.3.6,<2.0.0)
